msvsphere/rpmqc/__init__.py
msvsphere/rpmqc/cli.py
msvsphere/rpmqc/config.py
msvsphere/rpmqc/config_schema.py
msvsphere/rpmqc/file_utils.py
msvsphere/rpmqc/ima_utils.py
msvsphere/rpmqc/reporter.py
msvsphere/rpmqc/rpm_package.py
msvsphere/rpmqc/runner.py
msvsphere/rpmqc/inspectors/__init__.py
msvsphere/rpmqc/inspectors/pkg_base_inspector.py
msvsphere/rpmqc/inspectors/pkg_ima_inspector.py
msvsphere/rpmqc/inspectors/pkg_signature_inspector.py
msvsphere/rpmqc/inspectors/pkg_tags_inspector.py
rpmqc-0.0.4.dist-info/LICENSE
rpmqc-0.0.4.dist-info/METADATA
rpmqc-0.0.4.dist-info/WHEEL
rpmqc-0.0.4.dist-info/entry_points.txt
rpmqc-0.0.4.dist-info/top_level.txt
rpmqc-0.0.4.dist-info/RECORD
