Metadata-Version: 2.1
Name: rpmqc
Version: 0.0.4
Summary: The RPM packages quality control tool
Home-page: https://github.com/msvsphere/rpmqc
Author: Eugene Zamriy
Author-email: ezamriy@msvsphere-os.ru
License: GPL-2.0-or-later
Project-URL: Bug Tracker, https://github.com/msvsphere/rpmqc/issues
Classifier: Development Status :: 2 - Pre-Alpha
Classifier: Environment :: Console
Classifier: License :: OSI Approved :: GNU General Public License v2 or later (GPLv2+)
Classifier: Operating System :: POSIX :: Linux
Classifier: Programming Language :: Python :: 3
Classifier: Topic :: Software Development :: Quality Assurance
Classifier: Topic :: Software Development :: Testing
Classifier: Topic :: Utilities
Requires-Python: >=3.6
License-File: LICENSE
Requires-Dist: cryptography
Requires-Dist: pyyaml
Requires-Dist: schema
Requires-Dist: importlib-metadata ~=1.0 ; python_version < "3.8"
